{
    "ctLaunches": 32,
    "whenLastLaunch": "2022-03-11T03:59:12.726Z",
    "ctPictures": 18471,
    "whenLastPicture": "2022-03-11T15:07:00.744Z",
    "artists": {
        "artistmondrian": {
            "whenAdded": "2021-06-07T00:59:02.614Z",
            "whenLastCheck": "2022-03-11T14:46:00.952Z",
            "ctChecks": 347,
            "ctErrors": 1,
            "id": "1061465069026852865",
            "idLastTweet": "1501618416708378628",
            "ctPictures": 375,
            "whenLastPicture": "2022-03-11T14:46:00.952Z",
            "lastErrorMessage": "Unexpected token u in JSON at position 0"
        },
        "artlichtenstein": {
            "whenAdded": "2021-06-07T01:00:00.866Z",
            "whenLastCheck": "2022-03-11T14:47:00.076Z",
            "ctChecks": 347,
            "ctErrors": 1,
            "id": "893074379927691264",
            "idLastTweet": "1502010340871131136",
            "ctPictures": 466,
            "whenLastPicture": "2022-03-11T04:37:00.934Z",
            "lastErrorMessage": "Unexpected token u in JSON at position 0"
        },
        "artistescher": {
            "whenAdded": "2021-06-07T01:01:00.024Z",
            "whenLastCheck": "2022-03-11T14:48:00.181Z",
            "ctChecks": 347,
            "ctErrors": 1,
            "id": "893069482331131905",
            "idLastTweet": "1502012168765681671",
            "ctPictures": 542,
            "whenLastPicture": "2022-03-11T12:46:00.859Z",
            "lastErrorMessage": "Unexpected token u in JSON at position 0"
        },
        "artistottodix": {
            "whenAdded": "2021-06-07T01:02:00.211Z",
            "whenLastCheck": "2022-03-11T14:49:00.329Z",
            "ctChecks": 347,
            "ctErrors": 1,
            "id": "893066378227404800",
            "idLastTweet": "1501927570127953923",
            "ctPictures": 432,
            "whenLastPicture": "2022-03-11T04:39:00.539Z",
            "lastErrorMessage": "Unexpected token u in JSON at position 0"
        },
        "ArtistCortes": {
            "whenAdded": "2021-06-07T01:03:00.372Z",
            "whenLastCheck": "2022-03-11T14:50:00.468Z",
            "ctChecks": 347,
            "ctErrors": 1,
            "id": "893047548960579584",
            "idLastTweet": "1501730300128378881",
            "ctPictures": 406,
            "whenLastPicture": "2022-03-11T04:40:00.784Z",
            "lastErrorMessage": "Unexpected token u in JSON at position 0"
        },
        "artistwerefkin": {
            "whenAdded": "2021-06-07T01:04:00.528Z",
            "whenLastCheck": "2022-03-11T14:51:00.669Z",
            "ctChecks": 347,
            "ctErrors": 1,
            "id": "893045053807112192",
            "idLastTweet": "1497761280114970625",
            "ctPictures": 161,
            "whenLastPicture": "2022-03-11T04:41:00.988Z",
            "lastErrorMessage": "Unexpected token u in JSON at position 0"
        },
        "artprendergast": {
            "whenAdded": "2021-06-07T01:05:00.699Z",
            "whenLastCheck": "2022-03-11T15:07:00.744Z",
            "ctChecks": 347,
            "ctErrors": 1,
            "id": "893041173031473152",
            "idLastTweet": "1502007584995299330",
            "ctPictures": 467,
            "whenLastPicture": "2022-03-11T15:07:00.744Z",
            "lastErrorMessage": "Unexpected token u in JSON at position 0"
        },
        "artistbruegel": {
            "whenAdded": "2021-06-07T01:06:00.852Z",
            "whenLastCheck": "2022-03-11T15:08:00.845Z",
            "ctChecks": 347,
            "ctErrors": 1,
            "id": "820826766340132865",
            "idLastTweet": "1500951356869337090",
            "ctPictures": 316,
            "whenLastPicture": "2022-03-11T04:00:00.613Z",
            "lastErrorMessage": "Unexpected token u in JSON at position 0"
        },
        "artbotticelli": {
            "whenAdded": "2021-06-07T01:07:00.060Z",
            "whenLastCheck": "2022-03-11T14:09:00.295Z",
            "ctChecks": 346,
            "ctErrors": 1,
            "id": "820733384360083456",
            "idLastTweet": "1501548234011029510",
            "ctPictures": 381,
            "whenLastPicture": "2022-03-11T04:01:00.788Z",
            "lastErrorMessage": "Unexpected token u in JSON at position 0"
        },
        "artistpollock": {
            "whenAdded": "2021-06-07T01:08:00.255Z",
            "whenLastCheck": "2022-03-11T14:10:00.453Z",
            "ctChecks": 346,
            "ctErrors": 1,
            "id": "819807852566958085",
            "idLastTweet": "1501718411457576963",
            "ctPictures": 378,
            "whenLastPicture": "2022-03-11T04:02:00.873Z",
            "lastErrorMessage": "Unexpected token u in JSON at position 0"
        },
        "artistrothko": {
            "whenAdded": "2021-06-07T01:09:00.531Z",
            "whenLastCheck": "2022-03-11T14:11:00.547Z",
            "ctChecks": 346,
            "ctErrors": 1,
            "id": "819807672618741761",
            "idLastTweet": "1501950577860825088",
            "ctPictures": 427,
            "whenLastPicture": "2022-03-11T04:03:00.961Z",
            "lastErrorMessage": "Unexpected token u in JSON at position 0"
        },
        "artistdekooning": {
            "whenAdded": "2021-06-07T01:10:00.781Z",
            "whenLastCheck": "2022-03-11T14:12:00.676Z",
            "ctChecks": 346,
            "ctErrors": 0,
            "id": "819807576950874112",
            "idLastTweet": "1501698024455782408",
            "ctPictures": 389,
            "whenLastPicture": "2022-03-11T14:12:00.676Z"
        },
        "artistsargent": {
            "whenAdded": "2021-06-07T01:11:00.039Z",
            "whenLastCheck": "2022-03-11T14:13:00.833Z",
            "ctChecks": 346,
            "ctErrors": 0,
            "id": "819806874035843073",
            "idLastTweet": "1502034268255629314",
            "ctPictures": 509,
            "whenLastPicture": "2022-03-11T13:13:00.483Z"
        },
        "artisthopper": {
            "whenAdded": "2021-06-07T01:12:00.259Z",
            "whenLastCheck": "2022-03-11T14:14:00.934Z",
            "ctChecks": 346,
            "ctErrors": 0,
            "id": "819801657957490689",
            "idLastTweet": "1501941876429000707",
            "ctPictures": 411,
            "whenLastPicture": "2022-03-11T04:06:00.233Z"
        },
        "artistholbein": {
            "whenAdded": "2021-06-07T01:13:00.505Z",
            "whenLastCheck": "2022-03-11T14:16:00.164Z",
            "ctChecks": 346,
            "ctErrors": 1,
            "id": "819336666854944769",
            "idLastTweet": "1501948066533756930",
            "ctPictures": 409,
            "whenLastPicture": "2022-03-11T04:07:00.331Z",
            "lastErrorMessage": "Unexpected token u in JSON at position 0"
        },
        "artistraphael": {
            "whenAdded": "2021-06-07T01:14:00.771Z",
            "whenLastCheck": "2022-03-11T14:17:00.287Z",
            "ctChecks": 346,
            "ctErrors": 1,
            "id": "814301257317937152",
            "idLastTweet": "1501694538070769664",
            "ctPictures": 410,
            "whenLastPicture": "2022-03-11T04:08:00.407Z",
            "lastErrorMessage": "Unexpected token u in JSON at position 0"
        },
        "fanmichelangelo": {
            "whenAdded": "2021-06-07T01:15:00.950Z",
            "whenLastCheck": "2022-03-11T14:18:00.423Z",
            "ctChecks": 346,
            "ctErrors": 1,
            "id": "813230278097387521",
            "idLastTweet": "1501698368115990529",
            "ctPictures": 385,
            "whenLastPicture": "2022-03-11T04:09:00.511Z",
            "lastErrorMessage": "Unexpected token u in JSON at position 0"
        },
        "artistbosch": {
            "whenAdded": "2021-06-07T01:16:00.286Z",
            "whenLastCheck": "2022-03-11T14:19:00.613Z",
            "ctChecks": 346,
            "ctErrors": 0,
            "id": "813147420066545664",
            "idLastTweet": "1501631172727742467",
            "ctPictures": 387,
            "whenLastPicture": "2022-03-11T04:10:00.646Z"
        },
        "ArtistDaVinci": {
            "whenAdded": "2021-06-07T01:17:00.473Z",
            "whenLastCheck": "2022-03-11T14:20:00.758Z",
            "ctChecks": 346,
            "ctErrors": 0,
            "id": "812847929321025536",
            "idLastTweet": "1501725432273641472",
            "ctPictures": 411,
            "whenLastPicture": "2022-03-11T04:11:00.767Z"
        },
        "artistbrauner": {
            "whenAdded": "2021-06-07T01:18:00.662Z",
            "whenLastCheck": "2022-03-11T14:21:00.864Z",
            "ctChecks": 346,
            "ctErrors": 0,
            "id": "802625846439776256",
            "idLastTweet": "1501601105268162569",
            "ctPictures": 376,
            "whenLastPicture": "2022-03-11T05:13:00.176Z"
        },
        "artistklee": {
            "whenAdded": "2021-06-07T01:19:00.906Z",
            "whenLastCheck": "2022-03-11T14:22:00.986Z",
            "ctChecks": 346,
            "ctErrors": 0,
            "id": "802613662494191617",
            "idLastTweet": "1501988829267386369",
            "ctPictures": 522,
            "whenLastPicture": "2022-03-11T14:22:00.986Z"
        },
        "artist_dali": {
            "whenAdded": "2021-06-07T01:20:00.147Z",
            "whenLastCheck": "2022-03-11T14:24:00.284Z",
            "ctChecks": 346,
            "ctErrors": 0,
            "id": "798727210995687424",
            "idLastTweet": "1502051023594172428",
            "ctPictures": 572,
            "whenLastPicture": "2022-03-11T13:23:00.786Z"
        },
        "artistmagritte": {
            "whenAdded": "2021-06-07T01:21:00.422Z",
            "whenLastCheck": "2022-03-11T14:25:00.408Z",
            "ctChecks": 346,
            "ctErrors": 0,
            "id": "798654622361669632",
            "idLastTweet": "1501968036550557706",
            "ctPictures": 494,
            "whenLastPicture": "2022-03-11T04:15:00.986Z"
        },
        "artistzabaleta": {
            "whenAdded": "2021-06-07T01:22:00.654Z",
            "whenLastCheck": "2022-03-11T14:26:00.531Z",
            "ctChecks": 346,
            "ctErrors": 0,
            "id": "793617420518694912",
            "idLastTweet": "1498074607420588033",
            "ctPictures": 163,
            "whenLastPicture": "2022-03-11T04:16:00.119Z"
        },
        "artistduchamp": {
            "whenAdded": "2021-06-07T01:23:00.869Z",
            "whenLastCheck": "2022-03-11T14:27:00.649Z",
            "ctChecks": 346,
            "ctErrors": 1,
            "id": "792059498269585408",
            "idLastTweet": "1501944569402826754",
            "ctPictures": 413,
            "whenLastPicture": "2022-03-11T04:17:00.255Z",
            "lastErrorMessage": "Unexpected token u in JSON at position 0"
        },
        "artistmetzinger": {
            "whenAdded": "2021-06-07T01:24:00.121Z",
            "whenLastCheck": "2022-03-11T14:28:00.765Z",
            "ctChecks": 346,
            "ctErrors": 0,
            "id": "791715473800900609",
            "idLastTweet": "1500902064410529793",
            "ctPictures": 305,
            "whenLastPicture": "2022-03-11T05:19:00.519Z"
        },
        "artistmanet": {
            "whenAdded": "2021-06-07T01:25:00.404Z",
            "whenLastCheck": "2022-03-11T14:29:00.983Z",
            "ctChecks": 346,
            "ctErrors": 0,
            "id": "704710571187376129",
            "idLastTweet": "1501974104387297281",
            "ctPictures": 513,
            "whenLastPicture": "2022-03-11T14:29:00.983Z"
        },
        "artistdegas": {
            "whenAdded": "2021-06-07T01:26:00.677Z",
            "whenLastCheck": "2022-03-11T14:30:00.096Z",
            "ctChecks": 346,
            "ctErrors": 0,
            "id": "4740753023",
            "idLastTweet": "1489791395103707138",
            "ctPictures": 537,
            "whenLastPicture": "2022-02-20T23:55:00.824Z"
        },
        "artistmorisot": {
            "whenAdded": "2021-06-07T01:27:00.910Z",
            "whenLastCheck": "2022-03-11T14:31:00.308Z",
            "ctChecks": 346,
            "ctErrors": 0,
            "id": "4719083081",
            "idLastTweet": "1501729115329732608",
            "ctPictures": 403,
            "whenLastPicture": "2022-03-11T04:21:00.907Z"
        },
        "mackeaugust": {
            "whenAdded": "2021-06-07T01:28:00.131Z",
            "whenLastCheck": "2022-03-11T14:32:00.463Z",
            "ctChecks": 346,
            "ctErrors": 0,
            "id": "4493052314",
            "idLastTweet": "1501416857361948676",
            "ctPictures": 338,
            "whenLastPicture": "2022-03-11T04:22:00.121Z"
        },
        "franzmarcart": {
            "whenAdded": "2021-06-07T01:29:00.392Z",
            "whenLastCheck": "2022-03-11T14:33:00.580Z",
            "ctChecks": 346,
            "ctErrors": 0,
            "id": "4423533136",
            "idLastTweet": "1501568908549046280",
            "ctPictures": 361,
            "whenLastPicture": "2022-03-11T14:33:00.580Z"
        },
        "artistokeeffe": {
            "whenAdded": "2021-06-07T01:30:00.639Z",
            "whenLastCheck": "2022-03-11T14:34:00.715Z",
            "ctChecks": 346,
            "ctErrors": 0,
            "id": "4252296618",
            "idLastTweet": "1501952634797932551",
            "ctPictures": 442,
            "whenLastPicture": "2022-03-11T04:24:00.508Z"
        },
        "artpissarro": {
            "whenAdded": "2021-06-07T01:31:00.868Z",
            "whenLastCheck": "2022-03-11T14:35:00.866Z",
            "ctChecks": 346,
            "ctErrors": 0,
            "id": "4230124083",
            "idLastTweet": "1502055078903140361",
            "ctPictures": 554,
            "whenLastPicture": "2022-03-11T13:34:00.004Z"
        },
        "pablocubist": {
            "whenAdded": "2021-06-07T01:32:00.085Z",
            "whenLastCheck": "2022-03-11T14:36:01.003Z",
            "ctChecks": 346,
            "ctErrors": 0,
            "id": "4131418094",
            "idLastTweet": "1502063657060118554",
            "ctPictures": 534,
            "whenLastPicture": "2022-03-11T12:34:00.365Z"
        },
        "artistmatisse": {
            "whenAdded": "2021-06-07T01:33:00.264Z",
            "whenLastCheck": "2022-03-11T14:37:00.144Z",
            "ctChecks": 346,
            "ctErrors": 0,
            "id": "4007295494",
            "idLastTweet": "1502048848121933849",
            "ctPictures": 524,
            "whenLastPicture": "2022-03-11T09:32:00.478Z"
        },
        "vangoghartist": {
            "whenAdded": "2021-06-07T01:34:00.509Z",
            "whenLastCheck": "2022-03-11T14:38:00.284Z",
            "ctChecks": 346,
            "ctErrors": 0,
            "id": "3910165539",
            "idLastTweet": "1502063006355795971",
            "ctPictures": 533,
            "whenLastPicture": "2022-03-11T14:38:00.284Z"
        },
        "artistseurat": {
            "whenAdded": "2021-06-07T01:35:00.718Z",
            "whenLastCheck": "2022-03-11T14:39:00.399Z",
            "ctChecks": 346,
            "ctErrors": 0,
            "id": "3842270054",
            "idLastTweet": "1501777499273011202",
            "ctPictures": 408,
            "whenLastPicture": "2022-03-11T06:31:00.585Z"
        },
        "cezanneart": {
            "whenAdded": "2021-06-07T01:36:00.967Z",
            "whenLastCheck": "2022-03-11T14:40:00.530Z",
            "ctChecks": 346,
            "ctErrors": 0,
            "id": "3820960634",
            "idLastTweet": "1502047808274194436",
            "ctPictures": 553,
            "whenLastPicture": "2022-03-11T14:40:00.530Z"
        },
        "artfridakahlo": {
            "whenAdded": "2021-06-07T01:37:00.157Z",
            "whenLastCheck": "2022-03-11T14:41:00.654Z",
            "ctChecks": 346,
            "ctErrors": 1,
            "id": "3699312922",
            "idLastTweet": "1501371584442945536",
            "ctPictures": 325,
            "whenLastPicture": "2022-03-11T04:31:00.292Z",
            "lastErrorMessage": "Unexpected token u in JSON at position 0"
        },
        "artistchagall": {
            "whenAdded": "2021-06-07T01:38:00.381Z",
            "whenLastCheck": "2022-03-11T14:42:00.816Z",
            "ctChecks": 346,
            "ctErrors": 1,
            "id": "3655370114",
            "idLastTweet": "1502024037278662661",
            "ctPictures": 547,
            "whenLastPicture": "2022-03-11T14:42:00.816Z",
            "lastErrorMessage": "Unexpected token u in JSON at position 0"
        },
        "artistrivera": {
            "whenAdded": "2021-06-07T01:39:00.575Z",
            "whenLastCheck": "2022-03-11T14:43:00.961Z",
            "ctChecks": 346,
            "ctErrors": 1,
            "id": "3633729018",
            "idLastTweet": "1501687765318225922",
            "ctPictures": 414,
            "whenLastPicture": "2022-03-11T04:33:00.806Z",
            "lastErrorMessage": "Unexpected token u in JSON at position 0"
        },
        "artistgauguin": {
            "whenAdded": "2021-06-07T01:40:00.818Z",
            "whenLastCheck": "2022-03-11T14:44:00.183Z",
            "ctChecks": 346,
            "ctErrors": 1,
            "id": "3622154472",
            "idLastTweet": "1502024193868718085",
            "ctPictures": 525,
            "whenLastPicture": "2022-03-11T05:35:00.802Z",
            "lastErrorMessage": "Unexpected token u in JSON at position 0"
        },
        "artistkandinsky": {
            "whenAdded": "2021-06-07T01:41:00.034Z",
            "whenLastCheck": "2022-03-11T14:45:00.819Z",
            "ctChecks": 346,
            "ctErrors": 1,
            "id": "3555683713",
            "idLastTweet": "1501987115533488133",
            "ctPictures": 453,
            "whenLastPicture": "2022-03-11T04:35:00.310Z",
            "lastErrorMessage": "Unexpected token u in JSON at position 0"
        }
    },
    "fanAccountsList": [
        "artistmondrian",
        "artlichtenstein",
        "artistescher",
        "artistottodix",
        "ArtistCortes",
        "artistwerefkin",
        "artprendergast",
        "artistbruegel",
        "artbotticelli",
        "artistpollock",
        "artistrothko",
        "artistdekooning",
        "artistsargent",
        "artisthopper",
        "artistholbein",
        "artistraphael",
        "fanmichelangelo",
        "artistbosch",
        "ArtistDaVinci",
        "artistbrauner",
        "artistklee",
        "artist_dali",
        "artistmagritte",
        "artistzabaleta",
        "artistduchamp",
        "artistmetzinger",
        "artistmanet",
        "artistdegas",
        "artistmorisot",
        "mackeaugust",
        "franzmarcart",
        "artistokeeffe",
        "artpissarro",
        "pablocubist",
        "artistmatisse",
        "vangoghartist",
        "artistseurat",
        "cezanneart",
        "artfridakahlo",
        "artistchagall",
        "artistrivera",
        "artistgauguin",
        "artistkandinsky"
    ]
}