{
    "text": "Pablo Picasso, Marie-Thérèse Dreaming of Metamorphoses: Herself and the Sculptor Drinking with a Young Greek Actor Playing the Role of Minotaur (Marie-Thérèse rêvant de métamorphoses: elle-même et le sculpteur buvant avec un jeune..., 1933, published 1939 https://t.co/nhHSf5za9m https://t.co/tWjWFNNZ5s",
    "url": "http://pbs.twimg.com/media/E0q6iXaWEAAwjeb.jpg",
    "fname": "E0q6iXaWEAAwjeb.jpg",
    "w": 1884,
    "h": 1440,
    "name": "pablocubist",
    "id": "1390128537869430790",
    "when": "2021-05-06T02:25:01.057Z"
}